simbak/__init__.py
simbak/__main__.py
simbak/cli.py
simbak/config.py
simbak/exception.py
simbak/fileutil.py
simbak/logging.py
simbak/agent/__init__.py
simbak/agent/base.py
simbak/agent/normal.py
simbak/agent/rotating.py
simbak-0.4.2.dist-info/LICENSE
simbak-0.4.2.dist-info/METADATA
simbak-0.4.2.dist-info/WHEEL
simbak-0.4.2.dist-info/entry_points.txt
simbak-0.4.2.dist-info/top_level.txt
simbak-0.4.2.dist-info/RECORD
