Metadata-Version: 2.1
Name: simbak
Version: 0.4.2
Summary: A simple backup solution that's light and portable
Home-page: https://github.com/mark-bromell/simbak
Author: Mark Bromell
Author-email: markbromell.business@gmail.com
License: UNKNOWN
Project-URL: Source Code, https://github.com/mark-bromell/simbak
Platform: UNKNOWN
Classifier: Programming Language :: Python :: 3
Classifier: License :: OSI Approved :: MIT License
Classifier: Operating System :: OS Independent
Requires-Python: >=3.6
Requires-Dist: python-dotenv
